platyquest/__init__.py
platyquest/platyquest.py
platyquest-1.0.2.dist-info/METADATA
platyquest-1.0.2.dist-info/WHEEL
platyquest-1.0.2.dist-info/top_level.txt
platyquest-1.0.2.dist-info/RECORD
