Metadata-Version: 2.1
Name: platyquest
Version: 1.0.2
Summary: This platyquest is a part of platypy which helps in quests creation.
Home-page: UNKNOWN
Author: Python Rohan
Author-email: rohan9878787@gmail.com
License: UNKNOWN
Keywords: python,platyquest,questions,question,quest,quiz
Platform: UNKNOWN
Classifier: Development Status :: 1 - Planning
Classifier: Intended Audience :: Developers
Classifier: Programming Language :: Python :: 3
Classifier: Operating System :: Unix
Classifier: Operating System :: MacOS :: MacOS X
Classifier: Operating System :: Microsoft :: Windows
